pipeline_lib/__init__.py
pipeline_lib/execution.py
pipeline_lib/mp_execution.py
pipeline_lib/pipeline_task.py
pipeline_lib/py.typed
pipeline_lib/seq_execution.py
pipeline_lib/tr_execution.py
pipeline_lib/type_checking.py
pipeline_lib-0.3.1.dist-info/METADATA
pipeline_lib-0.3.1.dist-info/NOTICE.md
pipeline_lib-0.3.1.dist-info/WHEEL
pipeline_lib-0.3.1.dist-info/top_level.txt
pipeline_lib-0.3.1.dist-info/RECORD
