Metadata-Version: 2.1
Name: pipeline-lib
Version: 0.3.1
Summary: A streaming pipeline accelerator for Python
Classifier: Programming Language :: Python :: 3
Requires-Python: >=3.8
License-File: NOTICE.md
Requires-Dist: cloudpickle
Provides-Extra: dev
Requires-Dist: numpy ; extra == 'dev'
Requires-Dist: pytest ; extra == 'dev'
Requires-Dist: pytest-repeat ; extra == 'dev'
Requires-Dist: black ; extra == 'dev'
Requires-Dist: pylint ; extra == 'dev'
Requires-Dist: isort ; extra == 'dev'
Requires-Dist: mypy ; extra == 'dev'
Requires-Dist: colorama ; extra == 'dev'
Requires-Dist: build ; extra == 'dev'
Requires-Dist: twine ; extra == 'dev'
Requires-Dist: psutil ; extra == 'dev'
